{
  "$schema": "http://json-schema.org/draft-07/schema#",
  "type": "object",
  "title": "Ectropy Strategic Technical Analysis: Prisma, Graph Migration, MCP Implementation & Repository Synchronization",
  "version": "1.0.0",
  "lastUpdated": "2026-01-15",
  "metadata": {
    "originalPath": "C:\\Users\\luhte\\Source\\Repos\\luhtech\\Ectropy\\.roadmap\\features\\STRATEGIC_TECHNICAL_ANALYSIS_2026-01-16.md",
    "fileSize": 32484,
    "lineCount": 742,
    "lastModified": "2026-01-15T19:52:10.809302",
    "title": "Ectropy Strategic Technical Analysis: Prisma, Graph Migration, MCP Implementation & Repository Synchronization"
  },
  "content": {
    "raw": "# Ectropy Strategic Technical Analysis: Prisma, Graph Migration, MCP Implementation & Repository Synchronization\n\n**Document Version:** 1.0.0  \n**Date:** January 16, 2026  \n**Author:** Enterprise Architecture Session  \n**Status:** Strategic Planning Document\n\n---\n\n## Executive Summary\n\nThis document analyzes the next phases of Ectropy development across four critical dimensions:\n\n1. **Prisma Model Extensions** - Adding Contract-to-Operations models to existing M3 schema\n2. **Graph Database Migration** - Value proposition and lift assessment for PostgreSQL → Graph transition\n3. **MCP Tool Implementation** - Current state and roadmap for 39 total tools\n4. **Repository Synchronization** - Preparing luhtech/Ectropy for the January 17 split\n\n---\n\n## Part 1: Prisma Model Extension Analysis\n\n### 1.1 Current State (M3 Complete - 12 Models)\n\nThe existing `prisma/schema.prisma` contains 12 production-ready models from the Decision Lifecycle milestone:\n\n| Model                     | Purpose                       | URN Pattern                                        | Status    |\n| ------------------------- | ----------------------------- | -------------------------------------------------- | --------- |\n| `AuthorityLevel`          | 7-tier cascade definition     | `urn:luhtech:ectropy:authority-level:pm-level-{N}` | ✅ Active |\n| `Participant`             | Project stakeholder           | `urn:luhtech:{project}:participant:{id}`           | ✅ Active |\n| `Voxel`                   | 3D spatial decision container | `urn:luhtech:{project}:voxel:{id}`                 | ✅ Active |\n| `PMDecision`              | Construction decision         | `urn:luhtech:{project}:pm-decision:{id}`           | ✅ Active |\n| `VoxelDecisionAttachment` | Decision-to-voxel link        | N/A (join table)                                   | ✅ Active |\n| `ToleranceOverride`       | Pre-approved variance         | `urn:luhtech:{project}:tolerance:{id}`             | ✅ Active |\n| `PreApproval`             | Standing approval scope       | N/A (embedded)                                     | ✅ Active |\n| `VoxelAlert`              | Spatial alert                 | N/A (embedded)                                     | ✅ Active |\n| `Acknowledgment`          | Worker acknowledgment         | N/A (join table)                                   | ✅ Active |\n| `Consequence`             | Decision outcome tracking     | `urn:luhtech:{project}:consequence:{id}`           | ✅ Active |\n| `ScheduleProposal`        | Look-ahead modification       | `urn:luhtech:{project}:schedule-proposal:{id}`     | ✅ Active |\n| `Inspection`              | Field inspection record       | `urn:luhtech:{project}:inspection:{id}`            | ✅ Active |\n\n### 1.2 Required New Models (Contract-to-Operations)\n\nBased on the completed schema documentation, **15 additional Prisma models** are required:\n\n#### Contract Domain (3 models)\n\n```prisma\n// Contract.prisma - Governing contract for project\nmodel Contract {\n  id                String   @id @default(uuid()) @db.Uuid\n  urn               String   @unique @db.VarChar(200)\n  project_id        String   @map(\"project_id\") @db.Uuid\n  contract_id       String   @map(\"contract_id\") @db.VarChar(20) // CNTR-2026-0001\n  contract_type     ContractType @map(\"contract_type\")\n  title             String   @db.VarChar(255)\n  execution_date    DateTime @map(\"execution_date\") @db.Date\n  // ... authority cascade extracted from contract\n  authority_cascade Json     @map(\"authority_cascade\") @db.JsonB\n  // IPD-specific\n  is_ipd            Boolean  @default(false) @map(\"is_ipd\")\n  target_cost_ref   String?  @map(\"target_cost_ref\") @db.VarChar(200)\n  profit_at_risk    Json?    @map(\"profit_at_risk\") @db.JsonB\n  savings_distribution Json? @map(\"savings_distribution\") @db.JsonB\n  graph_metadata    Json?    @map(\"graph_metadata\") @db.JsonB\n  // Relations\n  project           Project  @relation(fields: [project_id], references: [id])\n  parties           ContractParty[]\n  // ... timestamps\n}\n\nmodel ContractParty {\n  id                String   @id @default(uuid()) @db.Uuid\n  contract_id       String   @map(\"contract_id\") @db.Uuid\n  party_role        PartyRole @map(\"party_role\")\n  company_name      String   @map(\"company_name\") @db.VarChar(255)\n  share_percentage  Decimal? @map(\"share_percentage\") @db.Decimal(5,2)\n  at_risk_percentage Decimal? @map(\"at_risk_percentage\") @db.Decimal(5,2)\n  // Relations\n  contract          Contract @relation(fields: [contract_id], references: [id])\n}\n\nmodel ContractTemplate {\n  id                String   @id @default(uuid()) @db.Uuid\n  urn               String   @unique @db.VarChar(200)\n  template_type     TemplateType @map(\"template_type\")\n  document_standard String   @map(\"document_standard\") @db.VarChar(50) // AIA, ConsensusDocs\n  authority_rules   Json     @map(\"authority_rules\") @db.JsonB\n  // ... clauses, sections\n}\n```\n\n#### IPD Governance Domain (3 models)\n\n```prisma\nmodel VotingSession {\n  id                String   @id @default(uuid()) @db.Uuid\n  urn               String   @unique @db.VarChar(200)\n  project_id        String   @map(\"project_id\") @db.Uuid\n  voting_body       VotingBody @map(\"voting_body\") // PMT or PET\n  topic             String   @db.Text\n  motion_text       String   @map(\"motion_text\") @db.Text\n  rule_type         VotingRule @map(\"rule_type\") // UNANIMOUS, SUPERMAJORITY, MAJORITY\n  status            VotingStatus @default(OPEN)\n  votes             Json     @db.JsonB // Array of vote objects\n  deadline          DateTime @db.Timestamptz(6)\n  // Relations\n  project           Project  @relation(fields: [project_id], references: [id])\n}\n\nmodel TargetCost {\n  id                String   @id @default(uuid()) @db.Uuid\n  urn               String   @unique @db.VarChar(200)\n  project_id        String   @map(\"project_id\") @db.Uuid\n  version           Int      @default(1)\n  status            TargetCostStatus @default(PROPOSED)\n  base_amount       Decimal  @map(\"base_amount\") @db.Decimal(15,2)\n  contingency_amount Decimal @map(\"contingency_amount\") @db.Decimal(15,2)\n  total_target_cost Decimal  @map(\"total_target_cost\") @db.Decimal(15,2)\n  adjustments       Json?    @db.JsonB\n  // Relations\n  project           Project  @relation(fields: [project_id], references: [id])\n}\n\nmodel SavingsDistribution {\n  id                String   @id @default(uuid()) @db.Uuid\n  urn               String   @unique @db.VarChar(200)\n  closeout_id       String   @map(\"closeout_id\") @db.Uuid\n  distribution_type DistributionType @map(\"distribution_type\") // SAVINGS or OVERRUN\n  total_amount      Decimal  @map(\"total_amount\") @db.Decimal(15,2)\n  distributions     Json     @db.JsonB // Array of party distributions\n  status            DistributionStatus @default(PENDING_APPROVAL)\n  // Relations\n  closeout          Closeout @relation(fields: [closeout_id], references: [id])\n}\n```\n\n#### Closeout Domain (3 models)\n\n```prisma\nmodel Closeout {\n  id                String   @id @default(uuid()) @db.Uuid\n  urn               String   @unique @db.VarChar(200)\n  project_id        String   @map(\"project_id\") @db.Uuid\n  status            CloseoutStatus @default(PRE_SUBSTANTIAL)\n  phases            Json     @db.JsonB // Phase status tracking\n  substantial_completion_date DateTime? @map(\"substantial_completion_date\") @db.Date\n  final_completion_date DateTime? @map(\"final_completion_date\") @db.Date\n  documentation_status Json   @map(\"documentation_status\") @db.JsonB\n  // Relations\n  project           Project  @relation(fields: [project_id], references: [id])\n  g704_certificate  G704Certificate?\n  punch_items       PunchItem[]\n  savings_distribution SavingsDistribution?\n}\n\nmodel G704Certificate {\n  id                String   @id @default(uuid()) @db.Uuid\n  urn               String   @unique @db.VarChar(200)\n  closeout_id       String   @unique @map(\"closeout_id\") @db.Uuid\n  certificate_number String  @map(\"certificate_number\") @db.VarChar(50)\n  substantial_completion_date DateTime @map(\"substantial_completion_date\") @db.Date\n  punch_list_deadline DateTime @map(\"punch_list_deadline\") @db.Date\n  signatures        Json     @db.JsonB // Signatory status\n  pdf_url           String?  @map(\"pdf_url\") @db.VarChar(500)\n  // Relations\n  closeout          Closeout @relation(fields: [closeout_id], references: [id])\n}\n\nmodel PunchItem {\n  id                String   @id @default(uuid()) @db.Uuid\n  urn               String   @unique @db.VarChar(200)\n  closeout_id       String   @map(\"closeout_id\") @db.Uuid\n  voxel_id          String   @map(\"voxel_id\") @db.Uuid\n  item_number       Int      @map(\"item_number\")\n  title             String   @db.VarChar(200)\n  category          PunchCategory\n  priority          PunchPriority\n  status            PunchStatus @default(OPEN)\n  assignee_urn      String?  @map(\"assignee_urn\") @db.VarChar(200)\n  sla_deadline      DateTime? @map(\"sla_deadline\") @db.Timestamptz(6)\n  completion_photos Json?    @map(\"completion_photos\") @db.JsonB\n  // Relations\n  closeout          Closeout @relation(fields: [closeout_id], references: [id])\n  voxel             Voxel    @relation(fields: [voxel_id], references: [id])\n}\n```\n\n#### Commissioning Domain (3 models)\n\n```prisma\nmodel CommissioningSystem {\n  id                String   @id @default(uuid()) @db.Uuid\n  urn               String   @unique @db.VarChar(200)\n  project_id        String   @map(\"project_id\") @db.Uuid\n  system_type       SystemType @map(\"system_type\") // HVAC, PLUMBING, etc.\n  system_tag        String   @map(\"system_tag\") @db.VarChar(50)\n  status            CxStatus @default(NOT_STARTED)\n  prefunctional_complete Boolean @default(false) @map(\"prefunctional_complete\")\n  fpt_complete      Boolean  @default(false) @map(\"fpt_complete\")\n  // Relations\n  project           Project  @relation(fields: [project_id], references: [id])\n  functional_tests  FunctionalTest[]\n  issues            CxIssue[]\n}\n\nmodel FunctionalTest {\n  id                String   @id @default(uuid()) @db.Uuid\n  urn               String   @unique @db.VarChar(200)\n  system_id         String   @map(\"system_id\") @db.Uuid\n  test_type         String   @map(\"test_type\") @db.VarChar(100)\n  outcome           FPTOutcome\n  measurements      Json?    @db.JsonB\n  deficiencies      Json?    @db.JsonB\n  performed_by      String   @map(\"performed_by\") @db.VarChar(200)\n  test_date         DateTime @map(\"test_date\") @db.Timestamptz(6)\n  // Relations\n  system            CommissioningSystem @relation(fields: [system_id], references: [id])\n}\n\nmodel CxIssue {\n  id                String   @id @default(uuid()) @db.Uuid\n  urn               String   @unique @db.VarChar(200)\n  system_id         String   @map(\"system_id\") @db.Uuid\n  description       String   @db.Text\n  severity          CxIssueSeverity\n  status            CxIssueStatus @default(OPEN)\n  root_cause_decisions Json? @map(\"root_cause_decisions\") @db.JsonB // URN array\n  resolution_decision_urn String? @map(\"resolution_decision_urn\") @db.VarChar(200)\n  // Relations\n  system            CommissioningSystem @relation(fields: [system_id], references: [id])\n}\n```\n\n#### Warranty/Operations Domain (3 models)\n\n```prisma\nmodel Warranty {\n  id                String   @id @default(uuid()) @db.Uuid\n  urn               String   @unique @db.VarChar(200)\n  project_id        String   @map(\"project_id\") @db.Uuid\n  warranty_type     WarrantyType @map(\"warranty_type\")\n  item_description  String   @map(\"item_description\") @db.VarChar(500)\n  vendor_name       String   @map(\"vendor_name\") @db.VarChar(255)\n  start_date        DateTime @map(\"start_date\") @db.Date\n  end_date          DateTime @map(\"end_date\") @db.Date\n  coverage_details  Json?    @map(\"coverage_details\") @db.JsonB\n  // Relations\n  project           Project  @relation(fields: [project_id], references: [id])\n  claims            WarrantyClaim[]\n}\n\nmodel WarrantyClaim {\n  id                String   @id @default(uuid()) @db.Uuid\n  urn               String   @unique @db.VarChar(200)\n  warranty_id       String   @map(\"warranty_id\") @db.Uuid\n  claim_type        ClaimType @map(\"claim_type\")\n  description       String   @db.Text\n  status            ClaimStatus @default(SUBMITTED)\n  related_decisions Json?    @map(\"related_decisions\") @db.JsonB // URN array for traceability\n  evidence          Json?    @db.JsonB\n  // Relations\n  warranty          Warranty @relation(fields: [warranty_id], references: [id])\n}\n\nmodel BuildingHistory {\n  id                String   @id @default(uuid()) @db.Uuid\n  urn               String   @unique @db.VarChar(200)\n  project_id        String   @map(\"project_id\") @db.Uuid\n  query_text        String   @map(\"query_text\") @db.Text\n  answer_text       String   @map(\"answer_text\") @db.Text\n  sources           Json     @db.JsonB // Decision/document URNs\n  queried_by        String   @map(\"queried_by\") @db.VarChar(200)\n  queried_at        DateTime @map(\"queried_at\") @db.Timestamptz(6)\n  // For caching common queries\n  query_hash        String?  @map(\"query_hash\") @db.VarChar(64)\n  // Relations\n  project           Project  @relation(fields: [project_id], references: [id])\n}\n```\n\n### 1.3 Migration Effort Estimate\n\n| Task                             | Hours        | Complexity |\n| -------------------------------- | ------------ | ---------- |\n| Define enums (15 new)            | 4            | Low        |\n| Create 15 models                 | 16           | Medium     |\n| Add relations to existing models | 8            | Medium     |\n| Generate migrations              | 4            | Low        |\n| Write seed data scripts          | 12           | Medium     |\n| Update TypeScript types          | 8            | Low        |\n| Integration testing              | 16           | Medium     |\n| **Total**                        | **68 hours** |            |\n\n---\n\n## Part 2: Graph Database Migration Analysis\n\n### 2.1 Current State: JSON-First with Graph Metadata\n\nThe V3 architecture uses **PostgreSQL with JSONB graph_metadata columns**:\n\n```json\n{\n  \"$id\": \"urn:luhtech:project-alpha:pm-decision:DEC-2026-0001\",\n  \"graphMetadata\": {\n    \"inEdges\": [\n      \"urn:luhtech:project-alpha:voxel:VOX-L2-MECH-047\",\n      \"urn:luhtech:project-alpha:participant:john-doe-pm\"\n    ],\n    \"outEdges\": [\"urn:luhtech:project-alpha:consequence:CONSQ-2026-0001\"]\n  }\n}\n```\n\n**Advantages:**\n\n- Single database to manage\n- Familiar SQL queries for most operations\n- Prisma ORM fully supported\n- Graph metadata preserved for future migration\n\n**Limitations:**\n\n- Graph traversal requires application-level code\n- No native Cypher/Gremlin query support\n- Complex joins for deep relationship queries\n- Performance degrades with >10,000 edges per query\n\n### 2.2 Migration Target: Neo4j or Dgraph\n\n#### Option A: Neo4j (Recommended)\n\n- **Query Language:** Cypher (intuitive, pattern-matching)\n- **Best For:** Complex relationship queries, path analysis\n- **APOC Library:** 300+ procedures for advanced graph operations\n- **Cost:** Enterprise license required for clustering\n\n#### Option B: Dgraph\n\n- **Query Language:** GraphQL-native\n- **Best For:** High-volume writes, horizontal scaling\n- **Advantage:** No separate license cost (Apache 2.0)\n- **Limitation:** Smaller ecosystem than Neo4j\n\n### 2.3 Value Proposition of Graph Migration\n\n| Use Case                               | PostgreSQL        | Graph DB             | Improvement        |\n| -------------------------------------- | ----------------- | -------------------- | ------------------ |\n| \"Find root cause of consequence X\"     | 5-7 JOINs, ~200ms | Single Cypher, ~20ms | **10x faster**     |\n| \"Show all decisions affecting Level 2\" | Complex subquery  | Pattern match        | **Simpler code**   |\n| \"Traverse 6 levels of escalation\"      | Recursive CTE     | `MATCH path=...`     | **Native support** |\n| \"Find patterns across 100 projects\"    | Impractical       | Graph analytics      | **New capability** |\n| \"Real-time decision impact preview\"    | Not feasible      | Graph projection     | **New capability** |\n\n### 2.4 Migration Lift Assessment\n\n#### Phase 1: Dual-Write Architecture (Low Risk)\n\n- Keep PostgreSQL as primary\n- Write graph_metadata to Neo4j in parallel\n- No production dependency on graph DB\n- **Effort:** 40 hours\n\n#### Phase 2: Graph-First Queries (Medium Risk)\n\n- Route relationship queries to Neo4j\n- Keep CRUD operations in PostgreSQL\n- Fallback to PostgreSQL if graph unavailable\n- **Effort:** 80 hours\n\n#### Phase 3: Full Migration (High Value, Higher Risk)\n\n- Move decision graph entirely to Neo4j\n- PostgreSQL for user/project CRUD only\n- Requires significant testing\n- **Effort:** 160 hours\n\n#### Total Estimated Lift: 280 hours (7 weeks)\n\n### 2.5 Recommendation\n\n**Start Phase 1 in Q3 2026 after Canadian pilot launch.**\n\nThe current PostgreSQL + JSONB architecture is sufficient for:\n\n- Pilot scale (single project, <10,000 decisions)\n- Demo scenarios\n- MVP launch\n\nGraph migration becomes critical when:\n\n- Multi-project portfolio queries required\n- Pattern recognition across projects\n- Real-time decision impact analysis\n\n---\n\n## Part 3: MCP Tool Implementation Analysis\n\n### 3.1 Current State: 17 Implemented Tools\n\nThe M2 milestone delivered 17 functional MCP tools in `mcp-tools/decision/mcp-decision-tools.json`:\n\n| Category               | Tool                         | Status         | Notes                      |\n| ---------------------- | ---------------------------- | -------------- | -------------------------- |\n| Decision Management    | `create_decision_request`    | ✅ Implemented | Full authority calculation |\n|                        | `analyze_decision_authority` | ✅ Implemented | 7-tier cascade logic       |\n|                        | `record_decision`            | ✅ Implemented | Immutable hash chain       |\n|                        | `create_decision_template`   | ✅ Implemented | Pattern library            |\n| Graph Operations       | `traverse_decision_graph`    | ✅ Implemented | Root cause analysis        |\n|                        | `attach_decision_to_voxels`  | ✅ Implemented | Auto BIM element lookup    |\n|                        | `get_voxel_decision_surface` | ✅ Implemented | Worker entry point         |\n| Voxel Operations       | `acknowledge_voxel_decision` | ✅ Implemented | GPS/UWB verification       |\n|                        | `find_voxels_for_work`       | ✅ Implemented | Task-based lookup          |\n|                        | `create_tolerance_override`  | ✅ Implemented | Pre-approval storage       |\n|                        | `calculate_voxel_savings`    | ✅ Implemented | Value metrics              |\n| Schedule Integration   | `create_schedule_proposal`   | ✅ Implemented | AI conflict detection      |\n|                        | `get_10day_lookahead`        | ✅ Implemented | Look-ahead view            |\n| Consequence Tracking   | `record_consequence`         | ✅ Implemented | Auto graph trace           |\n| Inspection Integration | `get_inspection_view`        | ✅ Implemented | Spatial decision view      |\n|                        | `record_inspection`          | ✅ Implemented | Sign-off workflow          |\n| Community              | `calculate_reward`           | ✅ Implemented | Gamification points        |\n\n### 3.2 Tools to Implement: 22 Remaining\n\nBased on the completed interfaces.json files:\n\n#### Contract Management (3 tools)\n\n| Tool                                   | Priority | Complexity | Dependencies         |\n| -------------------------------------- | -------- | ---------- | -------------------- |\n| `parse_contract_tool`                  | P1       | High       | PDF extraction, NLP  |\n| `extract_authority_cascade_tool`       | P1       | High       | Contract parser      |\n| `configure_project_from_contract_tool` | P1       | Medium     | AuthorityLevel model |\n\n#### IPD Governance (6 tools)\n\n| Tool                                | Priority | Complexity | Dependencies        |\n| ----------------------------------- | -------- | ---------- | ------------------- |\n| `initiate_pmt_vote_tool`            | P2       | Medium     | VotingSession model |\n| `cast_vote_tool`                    | P2       | Low        | VotingSession model |\n| `get_voting_status_tool`            | P2       | Low        | VotingSession model |\n| `escalate_to_pet_tool`              | P2       | Medium     | VotingSession model |\n| `update_target_cost_tool`           | P2       | Medium     | TargetCost model    |\n| `calculate_savings_projection_tool` | P2       | High       | Financial models    |\n\n#### Closeout (3 tools)\n\n| Tool                                   | Priority | Complexity | Dependencies          |\n| -------------------------------------- | -------- | ---------- | --------------------- |\n| `initiate_closeout_sequence_tool`      | P2       | Medium     | Closeout model        |\n| `generate_substantial_completion_tool` | P2       | High       | G704 PDF generation   |\n| `generate_final_accounting_tool`       | P2       | High       | Financial calculation |\n\n#### Commissioning (3 tools)\n\n| Tool                             | Priority | Complexity | Dependencies         |\n| -------------------------------- | -------- | ---------- | -------------------- |\n| `log_fpt_result_tool`            | P3       | Medium     | FunctionalTest model |\n| `link_cx_issue_to_decision_tool` | P3       | Medium     | Graph linkage        |\n| `generate_cx_documentation_tool` | P3       | High       | PDF generation       |\n\n#### Punch List (4 tools)\n\n| Tool                             | Priority | Complexity | Dependencies    |\n| -------------------------------- | -------- | ---------- | --------------- |\n| `create_punch_item_tool`         | P3       | Medium     | PunchItem model |\n| `update_punch_item_tool`         | P3       | Low        | PunchItem model |\n| `assign_punch_item_tool`         | P3       | Medium     | Twilio SMS      |\n| `validate_punch_completion_tool` | P3       | Medium     | GPS validation  |\n\n#### Warranty/Operations (3 tools)\n\n| Tool                           | Priority | Complexity | Dependencies           |\n| ------------------------------ | -------- | ---------- | ---------------------- |\n| `create_warranty_claim_tool`   | P3       | Medium     | Warranty model         |\n| `search_decision_archive_tool` | P3       | High       | Full-text search, RAG  |\n| `query_building_history_tool`  | P3       | High       | RAG, SEPPA integration |\n\n### 3.3 MCP Implementation Architecture\n\n```\n┌─────────────────────────────────────────────────────────────────┐\n│                      MCP Server (Port 4002)                     │\n├─────────────────────────────────────────────────────────────────┤\n│  Tool Registry  │  Tool Executor  │  Response Formatter         │\n├─────────────────────────────────────────────────────────────────┤\n│                                                                 │\n│  ┌─────────────┐  ┌─────────────┐  ┌─────────────┐             │\n│  │  Decision   │  │   Voxel     │  │  Schedule   │             │\n│  │   Tools     │  │   Tools     │  │   Tools     │             │\n│  │   (17)      │  │   (5)       │  │   (2)       │             │\n│  └──────┬──────┘  └──────┬──────┘  └──────┬──────┘             │\n│         │                │                │                     │\n│  ┌──────┴────────────────┴────────────────┴──────┐             │\n│  │            Prisma Client (PostgreSQL)          │             │\n│  │       + Graph Metadata (JSONB columns)         │             │\n│  └────────────────────────────────────────────────┘             │\n│                                                                 │\n│  ┌─────────────┐  ┌─────────────┐  ┌─────────────┐             │\n│  │  Contract   │  │    IPD      │  │  Closeout   │             │\n│  │   Tools     │  │   Tools     │  │   Tools     │             │\n│  │   (3) 📋    │  │   (6) 📋    │  │   (3) 📋    │             │\n│  └─────────────┘  └─────────────┘  └─────────────┘             │\n│                                                                 │\n│  ┌─────────────┐  ┌─────────────┐  ┌─────────────┐             │\n│  │Commissioning│  │  Punch List │  │  Warranty   │             │\n│  │   Tools     │  │   Tools     │  │   Tools     │             │\n│  │   (3) 📋    │  │   (4) 📋    │  │   (3) 📋    │             │\n│  └─────────────┘  └─────────────┘  └─────────────┘             │\n│                                                                 │\n│  📋 = Specified in interfaces.json, not yet implemented         │\n└─────────────────────────────────────────────────────────────────┘\n```\n\n### 3.4 Expected Functionality by Release\n\n| Release               | Tools | Functionality                                              |\n| --------------------- | ----- | ---------------------------------------------------------- |\n| **v1.2.0** (Current)  | 17    | Decision lifecycle, voxel operations, schedule integration |\n| **v1.3.0** (May 2026) | +9    | Contract parsing, IPD governance, basic closeout           |\n| **v1.4.0** (Sep 2026) | +7    | Full closeout, commissioning, punch list                   |\n| **v1.5.0** (Dec 2026) | +6    | Warranty, operations handoff, building history             |\n\n---\n\n## Part 4: Repository Synchronization Strategy\n\n### 4.1 Current Repository Structure\n\n```\nluhtech/Ectropy (Active Development)\n├── .roadmap/                    # V3 source of truth\n│   ├── roadmap.json\n│   ├── architecture.json\n│   ├── infrastructure-catalog.json\n│   ├── features/                # NEW - Feature documentation\n│   │   ├── decision-lifecycle/\n│   │   ├── contract-onboarding/\n│   │   ├── ipd-governance/\n│   │   ├── closeout/\n│   │   ├── commissioning/\n│   │   ├── punch-list/\n│   │   └── warranty-operations/\n│   └── schemas/                 # NEW - V3 schemas\n│       ├── contract/\n│       ├── ipd/\n│       ├── closeout/\n│       ├── commissioning/\n│       └── warranty/\n├── prisma/\n│   └── schema.prisma           # M3 models + future extensions\n├── apps/\n│   └── mcp-server/             # MCP implementation\n└── mcp-tools/\n    └── decision/               # Tool definitions\n```\n\n### 4.2 Target Split Structure (January 17, 2026)\n\n```\nectropy-ai/ectropy (Public - Apache 2.0)\n├── .roadmap/                    # Mirrored from luhtech\n│   ├── roadmap.json            # Quarterly milestones\n│   ├── features/               # Feature specifications\n│   └── schemas/                # V3 JSON schemas\n├── prisma/\n│   └── schema.prisma           # Core PM Decision models\n├── apps/\n│   └── mcp-server/             # Open-source MCP tools\n└── mcp-tools/\n    └── decision/\n\nluh-tech/Ectropy-Business (Private)\n├── .roadmap/                    # Business roadmap\n│   ├── roadmap-business.json   # Pricing, tiers, enterprise\n│   └── extensions.json         # Business feature extensions\n├── apps/\n│   └── assistant-service/      # SEPPA proprietary code\n│   └── phone-agent/            # Twilio integration\n└── business-tools/\n    └── slide-generator/        # Investor/customer decks\n```\n\n### 4.3 Files to Mirror Before Split\n\nThe following files MUST be present in luhtech/Ectropy `.roadmap/` before the split:\n\n| File/Directory                  | Status      | Action Required                        |\n| ------------------------------- | ----------- | -------------------------------------- |\n| `roadmap.json`                  | ✅ Current  | Verify Contract-to-Ops features listed |\n| `architecture.json`             | ✅ Current  | Verify new service ports               |\n| `infrastructure-catalog.json`   | ✅ Current  | Verify new services                    |\n| `features/decision-lifecycle/`  | ✅ Complete | No action                              |\n| `features/contract-onboarding/` | ✅ Complete | No action                              |\n| `features/ipd-governance/`      | ✅ Complete | No action                              |\n| `features/closeout/`            | ✅ Complete | No action                              |\n| `features/commissioning/`       | ✅ NEW      | Verify committed                       |\n| `features/punch-list/`          | ✅ NEW      | Verify committed                       |\n| `features/warranty-operations/` | ✅ NEW      | Verify committed                       |\n| `schemas/contract/`             | ✅ Complete | Verify committed                       |\n| `schemas/ipd/`                  | ✅ Complete | Verify committed                       |\n| `schemas/closeout/`             | ✅ Complete | Verify committed                       |\n| `schemas/commissioning/`        | ✅ Complete | Verify committed                       |\n| `schemas/warranty/`             | ✅ Complete | Verify committed                       |\n\n### 4.4 Synchronization Workflow\n\n```bash\n# Step 1: Commit all Contract-to-Operations work\ncd C:\\Users\\luhte\\Source\\Repos\\luhtech\\Ectropy\ngit add .roadmap/features/\ngit add .roadmap/schemas/\ngit commit -m \"feat(roadmap): Complete Contract-to-Operations feature documentation\n\nPhase 3-4 complete:\n- 4 new feature directories with FEATURE.json + interfaces.json\n- 13 new MCP tools specified\n- 15 V3-compliant schemas\n- Full REST API and webhook specifications\n\nTotal MCP tools now specified: 39 (17 implemented, 22 planned)\n\nRef: CONTRACT_TO_OPERATIONS_COMPLETION_REPORT.md\"\n\n# Step 2: Push to feature branch\ngit push origin feature/contract-to-operations\n\n# Step 3: Create PR for review\ngh pr create --title \"Contract-to-Operations Feature Documentation\" \\\n  --body \"Completes Phases 3-4 of Contract-to-Operations roadmap\"\n\n# Step 4: After merge, sync to Ectropy-Business\ncd C:\\Users\\luhte\\Source\\Repos\\luh-tech\\Ectropy-Business\ngit fetch upstream\ngit merge upstream/main\n\n# Step 5: Verify .roadmap mirror\ndiff -r .roadmap ../luhtech/Ectropy/.roadmap\n```\n\n### 4.5 Dashboard/Slide Generation Requirements\n\nFor the business-tools slide and dashboard generators to work correctly:\n\n1. **roadmap.json must contain:**\n   - All 6 Contract-to-Operations features in `features` array\n   - Milestone dates matching FEATURE.json files\n   - Quarterly deliverables aligned with releases\n\n2. **Feature directories must contain:**\n   - `FEATURE.json` with milestones, dependencies, graphMetadata\n   - `interfaces.json` with mcpTools, restApi, webhooks\n\n3. **Schema files must follow V3 pattern:**\n   - `$schema`, `$id` (URN), `schemaVersion: \"3.0.0\"`\n   - `graphMetadata` with `inEdges`/`outEdges`\n   - `meta` block with `sourceOfTruth`\n\n---\n\n## Part 5: Recommended Action Plan\n\n### Immediate (This Session)\n\n1. ✅ Complete feature documentation (DONE)\n2. ⬜ Commit all changes to feature branch\n3. ⬜ Verify JSON syntax validation passes\n4. ⬜ Create PR for review\n\n### Short-Term (Next Week)\n\n1. Merge Contract-to-Operations PR\n2. Sync .roadmap to luh-tech/Ectropy-Business\n3. Run slide-generator to verify data availability\n4. Run dashboard-generator for Notion sync\n\n### Medium-Term (Q1 2026)\n\n1. Implement Prisma models for Contract domain\n2. Implement first 3 Contract MCP tools\n3. Deploy to Canadian pilot environment\n4. Begin IPD governance tool implementation\n\n### Long-Term (Q2-Q4 2026)\n\n1. Complete all 22 MCP tools\n2. Begin Phase 1 graph migration (dual-write)\n3. Launch v1.3.0 with Contract/IPD features\n4. Evaluate graph migration Phase 2\n\n---\n\n## Appendix A: Git Commands for Immediate Commit\n\n```bash\n# Navigate to repository\ncd \"C:\\Users\\luhte\\Source\\Repos\\luhtech\\Ectropy\"\n\n# Stage new files\ngit add .roadmap/features/closeout/interfaces.json\ngit add .roadmap/features/commissioning/\ngit add .roadmap/features/punch-list/\ngit add .roadmap/features/warranty-operations/\ngit add .roadmap/features/CONTRACT_TO_OPERATIONS_COMPLETION_REPORT.md\n\n# Commit with detailed message\ngit commit -m \"feat(roadmap): Complete Contract-to-Operations Phases 3-4\n\nNEW FEATURE DOCUMENTATION:\n- closeout/interfaces.json (3 MCP tools)\n- commissioning/ (FEATURE.json + interfaces.json, 3 tools)\n- punch-list/ (FEATURE.json + interfaces.json, 4 tools)\n- warranty-operations/ (FEATURE.json + interfaces.json, 3 tools)\n\nTOTAL MCP TOOLS SPECIFIED: 39\n- 17 implemented (Decision Lifecycle M2)\n- 22 specified (Contract-to-Operations)\n\nAll files follow V3 enterprise patterns:\n- URN identifiers\n- GraphMetadata blocks\n- Schema version 3.0.0\n- Complete REST API + webhook specs\n\nPrepares repository for Jan 17 split to:\n- ectropy-ai/ectropy (public)\n- luh-tech/Ectropy-Business (private)\n\nRef: CONTRACT_TO_OPERATIONS_COMPLETION_REPORT.md\"\n\n# Push to feature branch\ngit push origin HEAD\n```\n\n---\n\n**Document ID:** ANALYSIS-PRISMA-GRAPH-MCP-SYNC-2026-01-16  \n**Classification:** Internal - Strategic Planning  \n**Review Cycle:** Before major phase gates\n",
    "sections": {
      "ectropy_strategic_technical_analysis_prisma_graph_migration_mcp_implementation_repository_synchronization": "**Document Version:** 1.0.0  \n**Date:** January 16, 2026  \n**Author:** Enterprise Architecture Session  \n**Status:** Strategic Planning Document\n\n---",
      "executive_summary": "This document analyzes the next phases of Ectropy development across four critical dimensions:\n\n1. **Prisma Model Extensions** - Adding Contract-to-Operations models to existing M3 schema\n2. **Graph Database Migration** - Value proposition and lift assessment for PostgreSQL → Graph transition\n3. **MCP Tool Implementation** - Current state and roadmap for 39 total tools\n4. **Repository Synchronization** - Preparing luhtech/Ectropy for the January 17 split\n\n---",
      "part_1_prisma_model_extension_analysis": "",
      "1_1_current_state_m3_complete_12_models": "The existing `prisma/schema.prisma` contains 12 production-ready models from the Decision Lifecycle milestone:\n\n| Model                     | Purpose                       | URN Pattern                                        | Status    |\n| ------------------------- | ----------------------------- | -------------------------------------------------- | --------- |\n| `AuthorityLevel`          | 7-tier cascade definition     | `urn:luhtech:ectropy:authority-level:pm-level-{N}` | ✅ Active |\n| `Participant`             | Project stakeholder           | `urn:luhtech:{project}:participant:{id}`           | ✅ Active |\n| `Voxel`                   | 3D spatial decision container | `urn:luhtech:{project}:voxel:{id}`                 | ✅ Active |\n| `PMDecision`              | Construction decision         | `urn:luhtech:{project}:pm-decision:{id}`           | ✅ Active |\n| `VoxelDecisionAttachment` | Decision-to-voxel link        | N/A (join table)                                   | ✅ Active |\n| `ToleranceOverride`       | Pre-approved variance         | `urn:luhtech:{project}:tolerance:{id}`             | ✅ Active |\n| `PreApproval`             | Standing approval scope       | N/A (embedded)                                     | ✅ Active |\n| `VoxelAlert`              | Spatial alert                 | N/A (embedded)                                     | ✅ Active |\n| `Acknowledgment`          | Worker acknowledgment         | N/A (join table)                                   | ✅ Active |\n| `Consequence`             | Decision outcome tracking     | `urn:luhtech:{project}:consequence:{id}`           | ✅ Active |\n| `ScheduleProposal`        | Look-ahead modification       | `urn:luhtech:{project}:schedule-proposal:{id}`     | ✅ Active |\n| `Inspection`              | Field inspection record       | `urn:luhtech:{project}:inspection:{id}`            | ✅ Active |",
      "1_2_required_new_models_contract_to_operations": "Based on the completed schema documentation, **15 additional Prisma models** are required:",
      "contract_domain_3_models": "```prisma\n// Contract.prisma - Governing contract for project\nmodel Contract {\n  id                String   @id @default(uuid()) @db.Uuid\n  urn               String   @unique @db.VarChar(200)\n  project_id        String   @map(\"project_id\") @db.Uuid\n  contract_id       String   @map(\"contract_id\") @db.VarChar(20) // CNTR-2026-0001\n  contract_type     ContractType @map(\"contract_type\")\n  title             String   @db.VarChar(255)\n  execution_date    DateTime @map(\"execution_date\") @db.Date\n  // ... authority cascade extracted from contract\n  authority_cascade Json     @map(\"authority_cascade\") @db.JsonB\n  // IPD-specific\n  is_ipd            Boolean  @default(false) @map(\"is_ipd\")\n  target_cost_ref   String?  @map(\"target_cost_ref\") @db.VarChar(200)\n  profit_at_risk    Json?    @map(\"profit_at_risk\") @db.JsonB\n  savings_distribution Json? @map(\"savings_distribution\") @db.JsonB\n  graph_metadata    Json?    @map(\"graph_metadata\") @db.JsonB\n  // Relations\n  project           Project  @relation(fields: [project_id], references: [id])\n  parties           ContractParty[]\n  // ... timestamps\n}\n\nmodel ContractParty {\n  id                String   @id @default(uuid()) @db.Uuid\n  contract_id       String   @map(\"contract_id\") @db.Uuid\n  party_role        PartyRole @map(\"party_role\")\n  company_name      String   @map(\"company_name\") @db.VarChar(255)\n  share_percentage  Decimal? @map(\"share_percentage\") @db.Decimal(5,2)\n  at_risk_percentage Decimal? @map(\"at_risk_percentage\") @db.Decimal(5,2)\n  // Relations\n  contract          Contract @relation(fields: [contract_id], references: [id])\n}\n\nmodel ContractTemplate {\n  id                String   @id @default(uuid()) @db.Uuid\n  urn               String   @unique @db.VarChar(200)\n  template_type     TemplateType @map(\"template_type\")\n  document_standard String   @map(\"document_standard\") @db.VarChar(50) // AIA, ConsensusDocs\n  authority_rules   Json     @map(\"authority_rules\") @db.JsonB\n  // ... clauses, sections\n}\n```",
      "ipd_governance_domain_3_models": "```prisma\nmodel VotingSession {\n  id                String   @id @default(uuid()) @db.Uuid\n  urn               String   @unique @db.VarChar(200)\n  project_id        String   @map(\"project_id\") @db.Uuid\n  voting_body       VotingBody @map(\"voting_body\") // PMT or PET\n  topic             String   @db.Text\n  motion_text       String   @map(\"motion_text\") @db.Text\n  rule_type         VotingRule @map(\"rule_type\") // UNANIMOUS, SUPERMAJORITY, MAJORITY\n  status            VotingStatus @default(OPEN)\n  votes             Json     @db.JsonB // Array of vote objects\n  deadline          DateTime @db.Timestamptz(6)\n  // Relations\n  project           Project  @relation(fields: [project_id], references: [id])\n}\n\nmodel TargetCost {\n  id                String   @id @default(uuid()) @db.Uuid\n  urn               String   @unique @db.VarChar(200)\n  project_id        String   @map(\"project_id\") @db.Uuid\n  version           Int      @default(1)\n  status            TargetCostStatus @default(PROPOSED)\n  base_amount       Decimal  @map(\"base_amount\") @db.Decimal(15,2)\n  contingency_amount Decimal @map(\"contingency_amount\") @db.Decimal(15,2)\n  total_target_cost Decimal  @map(\"total_target_cost\") @db.Decimal(15,2)\n  adjustments       Json?    @db.JsonB\n  // Relations\n  project           Project  @relation(fields: [project_id], references: [id])\n}\n\nmodel SavingsDistribution {\n  id                String   @id @default(uuid()) @db.Uuid\n  urn               String   @unique @db.VarChar(200)\n  closeout_id       String   @map(\"closeout_id\") @db.Uuid\n  distribution_type DistributionType @map(\"distribution_type\") // SAVINGS or OVERRUN\n  total_amount      Decimal  @map(\"total_amount\") @db.Decimal(15,2)\n  distributions     Json     @db.JsonB // Array of party distributions\n  status            DistributionStatus @default(PENDING_APPROVAL)\n  // Relations\n  closeout          Closeout @relation(fields: [closeout_id], references: [id])\n}\n```",
      "closeout_domain_3_models": "```prisma\nmodel Closeout {\n  id                String   @id @default(uuid()) @db.Uuid\n  urn               String   @unique @db.VarChar(200)\n  project_id        String   @map(\"project_id\") @db.Uuid\n  status            CloseoutStatus @default(PRE_SUBSTANTIAL)\n  phases            Json     @db.JsonB // Phase status tracking\n  substantial_completion_date DateTime? @map(\"substantial_completion_date\") @db.Date\n  final_completion_date DateTime? @map(\"final_completion_date\") @db.Date\n  documentation_status Json   @map(\"documentation_status\") @db.JsonB\n  // Relations\n  project           Project  @relation(fields: [project_id], references: [id])\n  g704_certificate  G704Certificate?\n  punch_items       PunchItem[]\n  savings_distribution SavingsDistribution?\n}\n\nmodel G704Certificate {\n  id                String   @id @default(uuid()) @db.Uuid\n  urn               String   @unique @db.VarChar(200)\n  closeout_id       String   @unique @map(\"closeout_id\") @db.Uuid\n  certificate_number String  @map(\"certificate_number\") @db.VarChar(50)\n  substantial_completion_date DateTime @map(\"substantial_completion_date\") @db.Date\n  punch_list_deadline DateTime @map(\"punch_list_deadline\") @db.Date\n  signatures        Json     @db.JsonB // Signatory status\n  pdf_url           String?  @map(\"pdf_url\") @db.VarChar(500)\n  // Relations\n  closeout          Closeout @relation(fields: [closeout_id], references: [id])\n}\n\nmodel PunchItem {\n  id                String   @id @default(uuid()) @db.Uuid\n  urn               String   @unique @db.VarChar(200)\n  closeout_id       String   @map(\"closeout_id\") @db.Uuid\n  voxel_id          String   @map(\"voxel_id\") @db.Uuid\n  item_number       Int      @map(\"item_number\")\n  title             String   @db.VarChar(200)\n  category          PunchCategory\n  priority          PunchPriority\n  status            PunchStatus @default(OPEN)\n  assignee_urn      String?  @map(\"assignee_urn\") @db.VarChar(200)\n  sla_deadline      DateTime? @map(\"sla_deadline\") @db.Timestamptz(6)\n  completion_photos Json?    @map(\"completion_photos\") @db.JsonB\n  // Relations\n  closeout          Closeout @relation(fields: [closeout_id], references: [id])\n  voxel             Voxel    @relation(fields: [voxel_id], references: [id])\n}\n```",
      "commissioning_domain_3_models": "```prisma\nmodel CommissioningSystem {\n  id                String   @id @default(uuid()) @db.Uuid\n  urn               String   @unique @db.VarChar(200)\n  project_id        String   @map(\"project_id\") @db.Uuid\n  system_type       SystemType @map(\"system_type\") // HVAC, PLUMBING, etc.\n  system_tag        String   @map(\"system_tag\") @db.VarChar(50)\n  status            CxStatus @default(NOT_STARTED)\n  prefunctional_complete Boolean @default(false) @map(\"prefunctional_complete\")\n  fpt_complete      Boolean  @default(false) @map(\"fpt_complete\")\n  // Relations\n  project           Project  @relation(fields: [project_id], references: [id])\n  functional_tests  FunctionalTest[]\n  issues            CxIssue[]\n}\n\nmodel FunctionalTest {\n  id                String   @id @default(uuid()) @db.Uuid\n  urn               String   @unique @db.VarChar(200)\n  system_id         String   @map(\"system_id\") @db.Uuid\n  test_type         String   @map(\"test_type\") @db.VarChar(100)\n  outcome           FPTOutcome\n  measurements      Json?    @db.JsonB\n  deficiencies      Json?    @db.JsonB\n  performed_by      String   @map(\"performed_by\") @db.VarChar(200)\n  test_date         DateTime @map(\"test_date\") @db.Timestamptz(6)\n  // Relations\n  system            CommissioningSystem @relation(fields: [system_id], references: [id])\n}\n\nmodel CxIssue {\n  id                String   @id @default(uuid()) @db.Uuid\n  urn               String   @unique @db.VarChar(200)\n  system_id         String   @map(\"system_id\") @db.Uuid\n  description       String   @db.Text\n  severity          CxIssueSeverity\n  status            CxIssueStatus @default(OPEN)\n  root_cause_decisions Json? @map(\"root_cause_decisions\") @db.JsonB // URN array\n  resolution_decision_urn String? @map(\"resolution_decision_urn\") @db.VarChar(200)\n  // Relations\n  system            CommissioningSystem @relation(fields: [system_id], references: [id])\n}\n```",
      "warranty_operations_domain_3_models": "```prisma\nmodel Warranty {\n  id                String   @id @default(uuid()) @db.Uuid\n  urn               String   @unique @db.VarChar(200)\n  project_id        String   @map(\"project_id\") @db.Uuid\n  warranty_type     WarrantyType @map(\"warranty_type\")\n  item_description  String   @map(\"item_description\") @db.VarChar(500)\n  vendor_name       String   @map(\"vendor_name\") @db.VarChar(255)\n  start_date        DateTime @map(\"start_date\") @db.Date\n  end_date          DateTime @map(\"end_date\") @db.Date\n  coverage_details  Json?    @map(\"coverage_details\") @db.JsonB\n  // Relations\n  project           Project  @relation(fields: [project_id], references: [id])\n  claims            WarrantyClaim[]\n}\n\nmodel WarrantyClaim {\n  id                String   @id @default(uuid()) @db.Uuid\n  urn               String   @unique @db.VarChar(200)\n  warranty_id       String   @map(\"warranty_id\") @db.Uuid\n  claim_type        ClaimType @map(\"claim_type\")\n  description       String   @db.Text\n  status            ClaimStatus @default(SUBMITTED)\n  related_decisions Json?    @map(\"related_decisions\") @db.JsonB // URN array for traceability\n  evidence          Json?    @db.JsonB\n  // Relations\n  warranty          Warranty @relation(fields: [warranty_id], references: [id])\n}\n\nmodel BuildingHistory {\n  id                String   @id @default(uuid()) @db.Uuid\n  urn               String   @unique @db.VarChar(200)\n  project_id        String   @map(\"project_id\") @db.Uuid\n  query_text        String   @map(\"query_text\") @db.Text\n  answer_text       String   @map(\"answer_text\") @db.Text\n  sources           Json     @db.JsonB // Decision/document URNs\n  queried_by        String   @map(\"queried_by\") @db.VarChar(200)\n  queried_at        DateTime @map(\"queried_at\") @db.Timestamptz(6)\n  // For caching common queries\n  query_hash        String?  @map(\"query_hash\") @db.VarChar(64)\n  // Relations\n  project           Project  @relation(fields: [project_id], references: [id])\n}\n```",
      "1_3_migration_effort_estimate": "| Task                             | Hours        | Complexity |\n| -------------------------------- | ------------ | ---------- |\n| Define enums (15 new)            | 4            | Low        |\n| Create 15 models                 | 16           | Medium     |\n| Add relations to existing models | 8            | Medium     |\n| Generate migrations              | 4            | Low        |\n| Write seed data scripts          | 12           | Medium     |\n| Update TypeScript types          | 8            | Low        |\n| Integration testing              | 16           | Medium     |\n| **Total**                        | **68 hours** |            |\n\n---",
      "part_2_graph_database_migration_analysis": "",
      "2_1_current_state_json_first_with_graph_metadata": "The V3 architecture uses **PostgreSQL with JSONB graph_metadata columns**:\n\n```json\n{\n  \"$id\": \"urn:luhtech:project-alpha:pm-decision:DEC-2026-0001\",\n  \"graphMetadata\": {\n    \"inEdges\": [\n      \"urn:luhtech:project-alpha:voxel:VOX-L2-MECH-047\",\n      \"urn:luhtech:project-alpha:participant:john-doe-pm\"\n    ],\n    \"outEdges\": [\"urn:luhtech:project-alpha:consequence:CONSQ-2026-0001\"]\n  }\n}\n```\n\n**Advantages:**\n\n- Single database to manage\n- Familiar SQL queries for most operations\n- Prisma ORM fully supported\n- Graph metadata preserved for future migration\n\n**Limitations:**\n\n- Graph traversal requires application-level code\n- No native Cypher/Gremlin query support\n- Complex joins for deep relationship queries\n- Performance degrades with >10,000 edges per query",
      "2_2_migration_target_neo4j_or_dgraph": "",
      "option_a_neo4j_recommended": "- **Query Language:** Cypher (intuitive, pattern-matching)\n- **Best For:** Complex relationship queries, path analysis\n- **APOC Library:** 300+ procedures for advanced graph operations\n- **Cost:** Enterprise license required for clustering",
      "option_b_dgraph": "- **Query Language:** GraphQL-native\n- **Best For:** High-volume writes, horizontal scaling\n- **Advantage:** No separate license cost (Apache 2.0)\n- **Limitation:** Smaller ecosystem than Neo4j",
      "2_3_value_proposition_of_graph_migration": "| Use Case                               | PostgreSQL        | Graph DB             | Improvement        |\n| -------------------------------------- | ----------------- | -------------------- | ------------------ |\n| \"Find root cause of consequence X\"     | 5-7 JOINs, ~200ms | Single Cypher, ~20ms | **10x faster**     |\n| \"Show all decisions affecting Level 2\" | Complex subquery  | Pattern match        | **Simpler code**   |\n| \"Traverse 6 levels of escalation\"      | Recursive CTE     | `MATCH path=...`     | **Native support** |\n| \"Find patterns across 100 projects\"    | Impractical       | Graph analytics      | **New capability** |\n| \"Real-time decision impact preview\"    | Not feasible      | Graph projection     | **New capability** |",
      "2_4_migration_lift_assessment": "",
      "phase_1_dual_write_architecture_low_risk": "- Keep PostgreSQL as primary\n- Write graph_metadata to Neo4j in parallel\n- No production dependency on graph DB\n- **Effort:** 40 hours",
      "phase_2_graph_first_queries_medium_risk": "- Route relationship queries to Neo4j\n- Keep CRUD operations in PostgreSQL\n- Fallback to PostgreSQL if graph unavailable\n- **Effort:** 80 hours",
      "phase_3_full_migration_high_value_higher_risk": "- Move decision graph entirely to Neo4j\n- PostgreSQL for user/project CRUD only\n- Requires significant testing\n- **Effort:** 160 hours",
      "total_estimated_lift_280_hours_7_weeks": "",
      "2_5_recommendation": "**Start Phase 1 in Q3 2026 after Canadian pilot launch.**\n\nThe current PostgreSQL + JSONB architecture is sufficient for:\n\n- Pilot scale (single project, <10,000 decisions)\n- Demo scenarios\n- MVP launch\n\nGraph migration becomes critical when:\n\n- Multi-project portfolio queries required\n- Pattern recognition across projects\n- Real-time decision impact analysis\n\n---",
      "part_3_mcp_tool_implementation_analysis": "",
      "3_1_current_state_17_implemented_tools": "The M2 milestone delivered 17 functional MCP tools in `mcp-tools/decision/mcp-decision-tools.json`:\n\n| Category               | Tool                         | Status         | Notes                      |\n| ---------------------- | ---------------------------- | -------------- | -------------------------- |\n| Decision Management    | `create_decision_request`    | ✅ Implemented | Full authority calculation |\n|                        | `analyze_decision_authority` | ✅ Implemented | 7-tier cascade logic       |\n|                        | `record_decision`            | ✅ Implemented | Immutable hash chain       |\n|                        | `create_decision_template`   | ✅ Implemented | Pattern library            |\n| Graph Operations       | `traverse_decision_graph`    | ✅ Implemented | Root cause analysis        |\n|                        | `attach_decision_to_voxels`  | ✅ Implemented | Auto BIM element lookup    |\n|                        | `get_voxel_decision_surface` | ✅ Implemented | Worker entry point         |\n| Voxel Operations       | `acknowledge_voxel_decision` | ✅ Implemented | GPS/UWB verification       |\n|                        | `find_voxels_for_work`       | ✅ Implemented | Task-based lookup          |\n|                        | `create_tolerance_override`  | ✅ Implemented | Pre-approval storage       |\n|                        | `calculate_voxel_savings`    | ✅ Implemented | Value metrics              |\n| Schedule Integration   | `create_schedule_proposal`   | ✅ Implemented | AI conflict detection      |\n|                        | `get_10day_lookahead`        | ✅ Implemented | Look-ahead view            |\n| Consequence Tracking   | `record_consequence`         | ✅ Implemented | Auto graph trace           |\n| Inspection Integration | `get_inspection_view`        | ✅ Implemented | Spatial decision view      |\n|                        | `record_inspection`          | ✅ Implemented | Sign-off workflow          |\n| Community              | `calculate_reward`           | ✅ Implemented | Gamification points        |",
      "3_2_tools_to_implement_22_remaining": "Based on the completed interfaces.json files:",
      "contract_management_3_tools": "| Tool                                   | Priority | Complexity | Dependencies         |\n| -------------------------------------- | -------- | ---------- | -------------------- |\n| `parse_contract_tool`                  | P1       | High       | PDF extraction, NLP  |\n| `extract_authority_cascade_tool`       | P1       | High       | Contract parser      |\n| `configure_project_from_contract_tool` | P1       | Medium     | AuthorityLevel model |",
      "ipd_governance_6_tools": "| Tool                                | Priority | Complexity | Dependencies        |\n| ----------------------------------- | -------- | ---------- | ------------------- |\n| `initiate_pmt_vote_tool`            | P2       | Medium     | VotingSession model |\n| `cast_vote_tool`                    | P2       | Low        | VotingSession model |\n| `get_voting_status_tool`            | P2       | Low        | VotingSession model |\n| `escalate_to_pet_tool`              | P2       | Medium     | VotingSession model |\n| `update_target_cost_tool`           | P2       | Medium     | TargetCost model    |\n| `calculate_savings_projection_tool` | P2       | High       | Financial models    |",
      "closeout_3_tools": "| Tool                                   | Priority | Complexity | Dependencies          |\n| -------------------------------------- | -------- | ---------- | --------------------- |\n| `initiate_closeout_sequence_tool`      | P2       | Medium     | Closeout model        |\n| `generate_substantial_completion_tool` | P2       | High       | G704 PDF generation   |\n| `generate_final_accounting_tool`       | P2       | High       | Financial calculation |",
      "commissioning_3_tools": "| Tool                             | Priority | Complexity | Dependencies         |\n| -------------------------------- | -------- | ---------- | -------------------- |\n| `log_fpt_result_tool`            | P3       | Medium     | FunctionalTest model |\n| `link_cx_issue_to_decision_tool` | P3       | Medium     | Graph linkage        |\n| `generate_cx_documentation_tool` | P3       | High       | PDF generation       |",
      "punch_list_4_tools": "| Tool                             | Priority | Complexity | Dependencies    |\n| -------------------------------- | -------- | ---------- | --------------- |\n| `create_punch_item_tool`         | P3       | Medium     | PunchItem model |\n| `update_punch_item_tool`         | P3       | Low        | PunchItem model |\n| `assign_punch_item_tool`         | P3       | Medium     | Twilio SMS      |\n| `validate_punch_completion_tool` | P3       | Medium     | GPS validation  |",
      "warranty_operations_3_tools": "| Tool                           | Priority | Complexity | Dependencies           |\n| ------------------------------ | -------- | ---------- | ---------------------- |\n| `create_warranty_claim_tool`   | P3       | Medium     | Warranty model         |\n| `search_decision_archive_tool` | P3       | High       | Full-text search, RAG  |\n| `query_building_history_tool`  | P3       | High       | RAG, SEPPA integration |",
      "3_3_mcp_implementation_architecture": "```\n┌─────────────────────────────────────────────────────────────────┐\n│                      MCP Server (Port 4002)                     │\n├─────────────────────────────────────────────────────────────────┤\n│  Tool Registry  │  Tool Executor  │  Response Formatter         │\n├─────────────────────────────────────────────────────────────────┤\n│                                                                 │\n│  ┌─────────────┐  ┌─────────────┐  ┌─────────────┐             │\n│  │  Decision   │  │   Voxel     │  │  Schedule   │             │\n│  │   Tools     │  │   Tools     │  │   Tools     │             │\n│  │   (17)      │  │   (5)       │  │   (2)       │             │\n│  └──────┬──────┘  └──────┬──────┘  └──────┬──────┘             │\n│         │                │                │                     │\n│  ┌──────┴────────────────┴────────────────┴──────┐             │\n│  │            Prisma Client (PostgreSQL)          │             │\n│  │       + Graph Metadata (JSONB columns)         │             │\n│  └────────────────────────────────────────────────┘             │\n│                                                                 │\n│  ┌─────────────┐  ┌─────────────┐  ┌─────────────┐             │\n│  │  Contract   │  │    IPD      │  │  Closeout   │             │\n│  │   Tools     │  │   Tools     │  │   Tools     │             │\n│  │   (3) 📋    │  │   (6) 📋    │  │   (3) 📋    │             │\n│  └─────────────┘  └─────────────┘  └─────────────┘             │\n│                                                                 │\n│  ┌─────────────┐  ┌─────────────┐  ┌─────────────┐             │\n│  │Commissioning│  │  Punch List │  │  Warranty   │             │\n│  │   Tools     │  │   Tools     │  │   Tools     │             │\n│  │   (3) 📋    │  │   (4) 📋    │  │   (3) 📋    │             │\n│  └─────────────┘  └─────────────┘  └─────────────┘             │\n│                                                                 │\n│  📋 = Specified in interfaces.json, not yet implemented         │\n└─────────────────────────────────────────────────────────────────┘\n```",
      "3_4_expected_functionality_by_release": "| Release               | Tools | Functionality                                              |\n| --------------------- | ----- | ---------------------------------------------------------- |\n| **v1.2.0** (Current)  | 17    | Decision lifecycle, voxel operations, schedule integration |\n| **v1.3.0** (May 2026) | +9    | Contract parsing, IPD governance, basic closeout           |\n| **v1.4.0** (Sep 2026) | +7    | Full closeout, commissioning, punch list                   |\n| **v1.5.0** (Dec 2026) | +6    | Warranty, operations handoff, building history             |\n\n---",
      "part_4_repository_synchronization_strategy": "",
      "4_1_current_repository_structure": "```\nluhtech/Ectropy (Active Development)\n├── .roadmap/                    # V3 source of truth\n│   ├── roadmap.json\n│   ├── architecture.json\n│   ├── infrastructure-catalog.json\n│   ├── features/                # NEW - Feature documentation\n│   │   ├── decision-lifecycle/\n│   │   ├── contract-onboarding/\n│   │   ├── ipd-governance/\n│   │   ├── closeout/\n│   │   ├── commissioning/\n│   │   ├── punch-list/\n│   │   └── warranty-operations/\n│   └── schemas/                 # NEW - V3 schemas\n│       ├── contract/\n│       ├── ipd/\n│       ├── closeout/\n│       ├── commissioning/\n│       └── warranty/\n├── prisma/\n│   └── schema.prisma           # M3 models + future extensions\n├── apps/\n│   └── mcp-server/             # MCP implementation\n└── mcp-tools/\n    └── decision/               # Tool definitions\n```",
      "4_2_target_split_structure_january_17_2026": "```\nectropy-ai/ectropy (Public - Apache 2.0)\n├── .roadmap/                    # Mirrored from luhtech\n│   ├── roadmap.json            # Quarterly milestones\n│   ├── features/               # Feature specifications\n│   └── schemas/                # V3 JSON schemas\n├── prisma/\n│   └── schema.prisma           # Core PM Decision models\n├── apps/\n│   └── mcp-server/             # Open-source MCP tools\n└── mcp-tools/\n    └── decision/\n\nluh-tech/Ectropy-Business (Private)\n├── .roadmap/                    # Business roadmap\n│   ├── roadmap-business.json   # Pricing, tiers, enterprise\n│   └── extensions.json         # Business feature extensions\n├── apps/\n│   └── assistant-service/      # SEPPA proprietary code\n│   └── phone-agent/            # Twilio integration\n└── business-tools/\n    └── slide-generator/        # Investor/customer decks\n```",
      "4_3_files_to_mirror_before_split": "The following files MUST be present in luhtech/Ectropy `.roadmap/` before the split:\n\n| File/Directory                  | Status      | Action Required                        |\n| ------------------------------- | ----------- | -------------------------------------- |\n| `roadmap.json`                  | ✅ Current  | Verify Contract-to-Ops features listed |\n| `architecture.json`             | ✅ Current  | Verify new service ports               |\n| `infrastructure-catalog.json`   | ✅ Current  | Verify new services                    |\n| `features/decision-lifecycle/`  | ✅ Complete | No action                              |\n| `features/contract-onboarding/` | ✅ Complete | No action                              |\n| `features/ipd-governance/`      | ✅ Complete | No action                              |\n| `features/closeout/`            | ✅ Complete | No action                              |\n| `features/commissioning/`       | ✅ NEW      | Verify committed                       |\n| `features/punch-list/`          | ✅ NEW      | Verify committed                       |\n| `features/warranty-operations/` | ✅ NEW      | Verify committed                       |\n| `schemas/contract/`             | ✅ Complete | Verify committed                       |\n| `schemas/ipd/`                  | ✅ Complete | Verify committed                       |\n| `schemas/closeout/`             | ✅ Complete | Verify committed                       |\n| `schemas/commissioning/`        | ✅ Complete | Verify committed                       |\n| `schemas/warranty/`             | ✅ Complete | Verify committed                       |",
      "4_4_synchronization_workflow": "```bash",
      "step_1_commit_all_contract_to_operations_work": "cd C:\\Users\\luhte\\Source\\Repos\\luhtech\\Ectropy\ngit add .roadmap/features/\ngit add .roadmap/schemas/\ngit commit -m \"feat(roadmap): Complete Contract-to-Operations feature documentation\n\nPhase 3-4 complete:\n- 4 new feature directories with FEATURE.json + interfaces.json\n- 13 new MCP tools specified\n- 15 V3-compliant schemas\n- Full REST API and webhook specifications\n\nTotal MCP tools now specified: 39 (17 implemented, 22 planned)\n\nRef: CONTRACT_TO_OPERATIONS_COMPLETION_REPORT.md\"",
      "step_2_push_to_feature_branch": "git push origin feature/contract-to-operations",
      "step_3_create_pr_for_review": "gh pr create --title \"Contract-to-Operations Feature Documentation\" \\\n  --body \"Completes Phases 3-4 of Contract-to-Operations roadmap\"",
      "step_4_after_merge_sync_to_ectropy_business": "cd C:\\Users\\luhte\\Source\\Repos\\luh-tech\\Ectropy-Business\ngit fetch upstream\ngit merge upstream/main",
      "step_5_verify_roadmap_mirror": "diff -r .roadmap ../luhtech/Ectropy/.roadmap\n```",
      "4_5_dashboard_slide_generation_requirements": "For the business-tools slide and dashboard generators to work correctly:\n\n1. **roadmap.json must contain:**\n   - All 6 Contract-to-Operations features in `features` array\n   - Milestone dates matching FEATURE.json files\n   - Quarterly deliverables aligned with releases\n\n2. **Feature directories must contain:**\n   - `FEATURE.json` with milestones, dependencies, graphMetadata\n   - `interfaces.json` with mcpTools, restApi, webhooks\n\n3. **Schema files must follow V3 pattern:**\n   - `$schema`, `$id` (URN), `schemaVersion: \"3.0.0\"`\n   - `graphMetadata` with `inEdges`/`outEdges`\n   - `meta` block with `sourceOfTruth`\n\n---",
      "part_5_recommended_action_plan": "",
      "immediate_this_session": "1. ✅ Complete feature documentation (DONE)\n2. ⬜ Commit all changes to feature branch\n3. ⬜ Verify JSON syntax validation passes\n4. ⬜ Create PR for review",
      "short_term_next_week": "1. Merge Contract-to-Operations PR\n2. Sync .roadmap to luh-tech/Ectropy-Business\n3. Run slide-generator to verify data availability\n4. Run dashboard-generator for Notion sync",
      "medium_term_q1_2026": "1. Implement Prisma models for Contract domain\n2. Implement first 3 Contract MCP tools\n3. Deploy to Canadian pilot environment\n4. Begin IPD governance tool implementation",
      "long_term_q2_q4_2026": "1. Complete all 22 MCP tools\n2. Begin Phase 1 graph migration (dual-write)\n3. Launch v1.3.0 with Contract/IPD features\n4. Evaluate graph migration Phase 2\n\n---",
      "appendix_a_git_commands_for_immediate_commit": "```bash",
      "navigate_to_repository": "cd \"C:\\Users\\luhte\\Source\\Repos\\luhtech\\Ectropy\"",
      "stage_new_files": "git add .roadmap/features/closeout/interfaces.json\ngit add .roadmap/features/commissioning/\ngit add .roadmap/features/punch-list/\ngit add .roadmap/features/warranty-operations/\ngit add .roadmap/features/CONTRACT_TO_OPERATIONS_COMPLETION_REPORT.md",
      "commit_with_detailed_message": "git commit -m \"feat(roadmap): Complete Contract-to-Operations Phases 3-4\n\nNEW FEATURE DOCUMENTATION:\n- closeout/interfaces.json (3 MCP tools)\n- commissioning/ (FEATURE.json + interfaces.json, 3 tools)\n- punch-list/ (FEATURE.json + interfaces.json, 4 tools)\n- warranty-operations/ (FEATURE.json + interfaces.json, 3 tools)\n\nTOTAL MCP TOOLS SPECIFIED: 39\n- 17 implemented (Decision Lifecycle M2)\n- 22 specified (Contract-to-Operations)\n\nAll files follow V3 enterprise patterns:\n- URN identifiers\n- GraphMetadata blocks\n- Schema version 3.0.0\n- Complete REST API + webhook specs\n\nPrepares repository for Jan 17 split to:\n- ectropy-ai/ectropy (public)\n- luh-tech/Ectropy-Business (private)\n\nRef: CONTRACT_TO_OPERATIONS_COMPLETION_REPORT.md\"",
      "push_to_feature_branch": "git push origin HEAD\n```\n\n---\n\n**Document ID:** ANALYSIS-PRISMA-GRAPH-MCP-SYNC-2026-01-16  \n**Classification:** Internal - Strategic Planning  \n**Review Cycle:** Before major phase gates"
    }
  }
}